oauthenticator/__init__.py
oauthenticator/_version.py
oauthenticator/auth0.py
oauthenticator/azuread.py
oauthenticator/bitbucket.py
oauthenticator/cilogon.py
oauthenticator/generic.py
oauthenticator/github.py
oauthenticator/gitlab.py
oauthenticator/globus.py
oauthenticator/google.py
oauthenticator/mediawiki.py
oauthenticator/oauth2.py
oauthenticator/openshift.py
oauthenticator/schemas/cilogon-schema.yaml
oauthenticator/tests/__init__.py
oauthenticator/tests/conftest.py
oauthenticator/tests/mocks.py
oauthenticator/tests/test_auth0.py
oauthenticator/tests/test_azuread.py
oauthenticator/tests/test_bitbucket.py
oauthenticator/tests/test_cilogon.py
oauthenticator/tests/test_generic.py
oauthenticator/tests/test_github.py
oauthenticator/tests/test_gitlab.py
oauthenticator/tests/test_globus.py
oauthenticator/tests/test_google.py
oauthenticator/tests/test_mediawiki.py
oauthenticator/tests/test_oauth2.py
oauthenticator/tests/test_openshift.py
oauthenticator-17.3.0.dist-info/LICENSE
oauthenticator-17.3.0.dist-info/METADATA
oauthenticator-17.3.0.dist-info/WHEEL
oauthenticator-17.3.0.dist-info/entry_points.txt
oauthenticator-17.3.0.dist-info/top_level.txt
oauthenticator-17.3.0.dist-info/RECORD
